{
  "val": "HPDWGGnKZbZqicjNYKYRBuBUlVYeIZXRhRRka",
  "id": 0,
  "children": [
    {
      "val": "pkBtpfGUslTxGhrwhnmjdNTRlVDlTJoDJQm",
      "id": 1,
      "children": [
        {
          "val": "UHIVcEkCBwFSlepDVpirovDuMxTkLXKfHGJu",
          "id": 2,
          "children": [
            {
              "val": "sLgTyGlDExTiYgJzyLOpx",
              "id": 3,
              "children": [
                {
                  "val": "NoqfFpNnNUHW",
                  "id": 4,
                  "children": [
                    {
                      "val": "jJEPk",
                      "id": 5,
                      "children": [
                        null,
                        null
                      ]
                    },
                    null
                  ]
                },
                {
                  "val": "RVC",
                  "id": 6,
                  "children": [
                    {
                      "val": "tpjMauiIVguSwShcnUmXwZxmlzfd",
                      "id": 7,
                      "children": [
                        null,
                        null
                      ]
                    },
                    null
                  ]
                }
              ]
            },
            {
              "val": "sYr",
              "id": 8,
              "children": [
                {
                  "val": "UHgtfYnKjhJWVtGYzykUKXBNJRe",
                  "id": 9,
                  "children": [
                    {
                      "val": "VUjbLYoYSibqLAudcCkw",
                      "id": 10,
                      "children": [
                        {
                          "val": "FOPjIHYtAjnMXsLRTQMDCf",
                          "id": 11,
                          "children": [
                            null,
                            null
                          ]
                        },
                        {
                          "val": "tEdKJluPjYBWPFTA",
                          "id": 12,
                          "children": [
                            null,
                            {
                              "val": "FnqBCiGqRJjwxoBvKdQybakCYwy",
                              "id": 13,
                              "children": [
                                null,
                                {
                                  "val": "WspzyGLDWdIszozXKgFehmMURKYUoTEsOoxXkJLjzRYIIU",
                                  "id": 14,
                                  "children": [
                                    null,
                                    null
                                  ]
                                }
                              ]
                            }
                          ]
                        }
                      ]
                    },
                    {
                      "val": "EuWslUNKH",
                      "id": 15,
                      "children": [
                        null,
                        {
                          "val": "IybfqSKIRTCFpKqBXabRHBIAxbdQzKPDVqdkrZaFNrdvTbZJ",
                          "id": 16,
                          "children": [
                            null,
                            {
                              "val": "ZBUaAyRJsZOXu",
                              "id": 17,
                              "children": [
                                {
                                  "val": "PJYWMWsrvqBsc",
                                  "id": 18,
                                  "children": [
                                    null,
                                    null
                                  ]
                                },
                                null
                              ]
                            }
                          ]
                        }
                      ]
                    }
                  ]
                },
                {
                  "val": "mBiztQLdAt",
                  "id": 19,
                  "children": [
                    {
                      "val": "tWBtddeQFaxamwvksObxVESDwLiBDwVPJTRullITQesivPZPDX",
                      "id": 20,
                      "children": [
                        {
                          "val": "FvlzBBuiOOAkNhNUcWWrOcHlBpgiu",
                          "id": 21,
                          "children": [
                            null,
                            {
                              "val": "mQMfFAdwIdFTC",
                              "id": 22,
                              "children": [
                                {
                                  "val": "niStGyXrx",
                                  "id": 23,
                                  "children": [
                                    null,
                                    null
                                  ]
                                },
                                {
                                  "val": "sZWObgCdnXIRRpYMkvkKpeWQdvDBeyjUdHXLtl",
                                  "id": 24,
                                  "children": [
                                    {
                                      "val": "Oh",
                                      "id": 25,
                                      "children": [
                                        null,
                                        null
                                      ]
                                    },
                                    null
                                  ]
                                }
                              ]
                            }
                          ]
                        },
                        {
                          "val": "uOghlsXGheuamKbOQMFkrIMHrWvUmTExAl",
                          "id": 26,
                          "children": [
                            {
                              "val": "XXsKiQdIVwbzBXXQXetKKEbKGLrmLtReZEOHacAJjfieWOjduK",
                              "id": 27,
                              "children": [
                                {
                                  "val": "CVoKkEyGhCMFHzOAcAGRIOESnGlQKaWLhDtDXGalzMyh",
                                  "id": 28,
                                  "children": [
                                    {
                                      "val": "UAQYUNbHsRbEeeCuoMtKK",
                                      "id": 29,
                                      "children": [
                                        null,
                                        null
                                      ]
                                    },
                                    null
                                  ]
                                },
                                {
                                  "val": "TNkOEtmIZx",
                                  "id": 30,
                                  "children": [
                                    null,
                                    null
                                  ]
                                }
                              ]
                            },
                            null
                          ]
                        }
                      ]
                    },
                    {
                      "val": "RHxeriJG",
                      "id": 31,
                      "children": [
                        {
                          "val": "VjCtXpTBKMDipZLBihjeRtJTfWihgQkcykkSYRXmkDIMya",
                          "id": 32,
                          "children": [
                            {
                              "val": "LGfRxSWIwXsobsrAEOiLCTZrjFwfzCcwRRPbCSuiZa",
                              "id": 33,
                              "children": [
                                null,
                                null
                              ]
                            },
                            {
                              "val": "vzVhEExKOuHxqFiEeotVcmYika",
                              "id": 34,
                              "children": [
                                {
                                  "val": "KHZibqsaeOBVgBtZHOmjiEvWqTnkcpCgn",
                                  "id": 35,
                                  "children": [
                                    {
                                      "val": "TYgtZrdGcMcXBN",
                                      "id": 36,
                                      "children": [
                                        null,
                                        null
                                      ]
                                    },
                                    {
                                      "val": "ZCwEtsvyG",
                                      "id": 37,
                                      "children": [
                                        null,
                                        null
                                      ]
                                    }
                                  ]
                                },
                                null
                              ]
                            }
                          ]
                        },
                        null
                      ]
                    }
                  ]
                }
              ]
            }
          ]
        },
        {
          "val": "YksOacQVlEXPWe",
          "id": 38,
          "children": [
            {
              "val": "aShEoHYEqzfaENCgXPKZSXSSsgItTwLgTpE",
              "id": 39,
              "children": [
                null,
                null
              ]
            },
            {
              "val": "knLjzfQJTELGnpWzxgwMvhAqVHfPauWDCvzPgzsXbr",
              "id": 40,
              "children": [
                null,
                null
              ]
            }
          ]
        }
      ]
    },
    {
      "val": "cgH",
      "id": 41,
      "children": [
        {
          "val": "PgWTDXJkWUPGxadwDxtZxUe",
          "id": 42,
          "children": [
            {
              "val": "CXkQacAWofsnfdWdTNbGMRpjHvKuDLwmMmPPGTQcJ",
              "id": 43,
              "children": [
                {
                  "val": "FuglIvuGmXcoJOnvGQoJhZTJbTttU",
                  "id": 44,
                  "children": [
                    {
                      "val": "bbrwdsTCsOhzRKOMVDonhK",
                      "id": 45,
                      "children": [
                        null,
                        {
                          "val": "PuKBePbSdXEJnlBmtjaHtaceXAVirwhrRbFAfpzWlbmXPZpVdG",
                          "id": 46,
                          "children": [
                            null,
                            null
                          ]
                        }
                      ]
                    },
                    {
                      "val": "ieoRzDa",
                      "id": 47,
                      "children": [
                        null,
                        null
                      ]
                    }
                  ]
                },
                {
                  "val": "hJtFHciwgMFEILtb",
                  "id": 48,
                  "children": [
                    {
                      "val": "RDfTFDsmNpAHNmbyafNLTmYHqZinPPcwHaQWwtKY",
                      "id": 49,
                      "children": [
                        null,
                        {
                          "val": "CRrbUGXjPDcYmRGIaSghXLErQajmjY",
                          "id": 50,
                          "children": [
                            {
                              "val": "GGJNgANsXFhzMwKdV",
                              "id": 51,
                              "children": [
                                {
                                  "val": "Mn",
                                  "id": 52,
                                  "children": [
                                    {
                                      "val": "rurhuBnRvWVCod",
                                      "id": 53,
                                      "children": [
                                        null,
                                        null
                                      ]
                                    },
                                    null
                                  ]
                                },
                                null
                              ]
                            },
                            {
                              "val": "EAQxjecMnFbFFp",
                              "id": 54,
                              "children": [
                                null,
                                null
                              ]
                            }
                          ]
                        }
                      ]
                    },
                    {
                      "val": "bnErBxOMtInkXpPjHzBBeaCPZYePYv",
                      "id": 55,
                      "children": [
                        {
                          "val": "DKc",
                          "id": 56,
                          "children": [
                            null,
                            {
                              "val": "fTIdglyCbYydx",
                              "id": 57,
                              "children": [
                                null,
                                null
                              ]
                            }
                          ]
                        },
                        {
                          "val": "hMIzgePEswNOUjwHzHzjhlQjrihRhqxhtwLwWpNpAONw",
                          "id": 58,
                          "children": [
                            null,
                            {
                              "val": "YmvqkFVyEhUmTSgIPUsiMXvkEpfJKfSAsyuqK",
                              "id": 59,
                              "children": [
                                {
                                  "val": "WPanLBMQEDIIkVcyFYFPYxHGpoFIiaqcZZMDIvsXMkCnWDEKgx",
                                  "id": 60,
                                  "children": [
                                    null,
                                    null
                                  ]
                                },
                                null
                              ]
                            }
                          ]
                        }
                      ]
                    }
                  ]
                }
              ]
            },
            {
              "val": "qoDXYtNzeQketyxQfOnuHCFTeljLlVCYsUZxxAjMtqUSZ",
              "id": 61,
              "children": [
                {
                  "val": "BpEYGiuDIiqqDItweipKKbetTvzdaBknRVYJ",
                  "id": 62,
                  "children": [
                    {
                      "val": "VzoDCvlIHIgxvduwkgMsEneIeQ",
                      "id": 63,
                      "children": [
                        {
                          "val": "PSgTmaRsMQKVlSQwAnzKlAgHkPtdgMvCwqhp",
                          "id": 64,
                          "children": [
                            {
                              "val": "KhbmaFBldKtyBcYqWyeSpHJpbnF",
                              "id": 65,
                              "children": [
                                null,
                                null
                              ]
                            },
                            null
                          ]
                        },
                        null
                      ]
                    },
                    {
                      "val": "uxnO",
                      "id": 66,
                      "children": [
                        null,
                        {
                          "val": "gncvQwvFRSqvdkRdmPKYeXMNOoWDdEPDvGBhnpdoudacTo",
                          "id": 67,
                          "children": [
                            null,
                            {
                              "val": "YCAPyPSmCjSxdzFzMgHjpBTRHFe",
                              "id": 68,
                              "children": [
                                null,
                                {
                                  "val": "dvkylAlCTXbntBPYaMvPuqpHJenznIVHNPTNR",
                                  "id": 69,
                                  "children": [
                                    {
                                      "val": "PYYCaPdNWJRMMhuZsl",
                                      "id": 70,
                                      "children": [
                                        {
                                          "val": "LktDLpEyY",
                                          "id": 71,
                                          "children": [
                                            null,
                                            null
                                          ]
                                        },
                                        {
                                          "val": "Yw",
                                          "id": 72,
                                          "children": [
                                            null,
                                            null
                                          ]
                                        }
                                      ]
                                    },
                                    {
                                      "val": "BkWMowuPbIuHVJzPKsGjABL",
                                      "id": 73,
                                      "children": [
                                        null,
                                        null
                                      ]
                                    }
                                  ]
                                }
                              ]
                            }
                          ]
                        }
                      ]
                    }
                  ]
                },
                {
                  "val": "CDuKoAzAdhGbGEoghCyas",
                  "id": 74,
                  "children": [
                    {
                      "val": "cqCfclwJNnQyaVClInoROPlCTzvUATFth",
                      "id": 75,
                      "children": [
                        {
                          "val": "veipMoBbEN",
                          "id": 76,
                          "children": [
                            null,
                            null
                          ]
                        },
                        null
                      ]
                    },
                    {
                      "val": "RWeHRshALMYzpiOSxEaeeQjXAiVMUs",
                      "id": 77,
                      "children": [
                        null,
                        null
                      ]
                    }
                  ]
                }
              ]
            }
          ]
        },
        {
          "val": "cub",
          "id": 78,
          "children": [
            {
              "val": "HvhHffByxwvfbRnho",
              "id": 79,
              "children": [
                {
                  "val": "HgzZChkowqQFEQkwtayQdWQMDxhTGOAoRoqiIJsUemSYNgkuB",
                  "id": 80,
                  "children": [
                    {
                      "val": "vkZIwOyibFgSOdHqwBnjULFSo",
                      "id": 81,
                      "children": [
                        null,
                        null
                      ]
                    },
                    null
                  ]
                },
                {
                  "val": "hIOISPMHjWTUBMCVnugWbaqscUTgzVFOufAuKikp",
                  "id": 82,
                  "children": [
                    null,
                    {
                      "val": "xJBETIWdT",
                      "id": 83,
                      "children": [
                        {
                          "val": "gDWzf",
                          "id": 84,
                          "children": [
                            null,
                            null
                          ]
                        },
                        {
                          "val": "DUAKWvoIaUXWLiJodhHTFARxjNxaYQqQYbaLaYwu",
                          "id": 85,
                          "children": [
                            null,
                            null
                          ]
                        }
                      ]
                    }
                  ]
                }
              ]
            },
            {
              "val": "BSWxcYRYiJSkzrMTGmCcZDsKe",
              "id": 86,
              "children": [
                {
                  "val": "OEaoOmikERHQNBEhgSQpXXVERfbjuxeIOyzbEVdwxUVKePICW",
                  "id": 87,
                  "children": [
                    null,
                    null
                  ]
                },
                {
                  "val": "loHwROdiHNotntsOfQMmZqPGquulJvERCEZUkkaZpDIUbKt",
                  "id": 88,
                  "children": [
                    null,
                    null
                  ]
                }
              ]
            }
          ]
        }
      ]
    }
  ]
}